{
  "version": "wastewater_v1",
  "utility_system": "wastewater",
  "description": "Wastewater Data Health V1 QA rules for staged gravity mains and manholes.",
  "defaults": {
    "endpoint_tolerance_feet": 3,
    "warning_tolerance_feet": 10,
    "short_pipe_threshold_feet": 5,
    "high_endpoint_degree": 6
  },
  "rules": [
    {
      "rule_code": "WW_ID_001",
      "name": "Missing manhole asset ID",
      "description": "Manhole has no mapped asset identifier.",
      "category": "Identity",
      "applicable_layer": "wastewater_manhole",
      "severity": "high",
      "enabled": true,
      "required_semantic_fields": ["asset_id"],
      "parameters": {},
      "detection_method": "Blank check on mapped manhole asset ID field.",
      "limitation": "Asset ID mapping is inferred from field metadata and safe aggregate patterns.",
      "recommended_action": "Confirm the authoritative manhole ID and populate missing values in a governed edit workflow."
    },
    {
      "rule_code": "WW_ID_002",
      "name": "Duplicate manhole asset ID",
      "description": "Multiple manholes share the same mapped asset identifier.",
      "category": "Identity",
      "applicable_layer": "wastewater_manhole",
      "severity": "high",
      "enabled": true,
      "required_semantic_fields": ["asset_id"],
      "parameters": {},
      "detection_method": "Duplicate check on nonblank mapped manhole asset ID values.",
      "limitation": "Candidate duplicates require steward review before confirming.",
      "recommended_action": "Review duplicate manhole IDs against source records and assign unique identifiers where appropriate."
    },
    {
      "rule_code": "WW_ID_003",
      "name": "Missing pipe asset ID",
      "description": "Gravity main has no mapped asset identifier.",
      "category": "Identity",
      "applicable_layer": "wastewater_gravity_main",
      "severity": "high",
      "enabled": true,
      "required_semantic_fields": ["asset_id"],
      "parameters": {},
      "detection_method": "Blank check on mapped pipe asset ID field.",
      "limitation": "Asset ID mapping is inferred from field metadata and safe aggregate patterns.",
      "recommended_action": "Confirm the authoritative pipe ID and populate missing values in a governed edit workflow."
    },
    {
      "rule_code": "WW_ID_004",
      "name": "Duplicate pipe asset ID",
      "description": "Multiple gravity mains share the same mapped asset identifier.",
      "category": "Identity",
      "applicable_layer": "wastewater_gravity_main",
      "severity": "high",
      "enabled": true,
      "required_semantic_fields": ["asset_id"],
      "parameters": {},
      "detection_method": "Duplicate check on nonblank mapped pipe asset ID values.",
      "limitation": "Candidate duplicates require steward review before confirming.",
      "recommended_action": "Review duplicate pipe IDs against source records and assign unique identifiers where appropriate."
    },
    {
      "rule_code": "WW_ATTR_001",
      "name": "Missing pipe diameter",
      "description": "Gravity main diameter is blank or nonpositive.",
      "category": "Attributes",
      "applicable_layer": "wastewater_gravity_main",
      "severity": "medium",
      "enabled": true,
      "required_semantic_fields": ["diameter"],
      "parameters": {},
      "detection_method": "Blank and numeric validity check on mapped diameter field.",
      "limitation": "Diameter units are inferred from source convention and require confirmation.",
      "recommended_action": "Populate missing diameter from source records or engineering review."
    },
    {
      "rule_code": "WW_ATTR_002",
      "name": "Missing pipe material",
      "description": "Gravity main material is blank.",
      "category": "Attributes",
      "applicable_layer": "wastewater_gravity_main",
      "severity": "medium",
      "enabled": true,
      "required_semantic_fields": ["material"],
      "parameters": {},
      "detection_method": "Blank check on mapped material field.",
      "limitation": "Material codes are not domain-constrained in the staged source.",
      "recommended_action": "Populate material from source records or mark as unknown under an approved domain."
    },
    {
      "rule_code": "WW_ATTR_003",
      "name": "Missing pipe status",
      "description": "Gravity main lifecycle or operating status is blank.",
      "category": "Attributes",
      "applicable_layer": "wastewater_gravity_main",
      "severity": "medium",
      "enabled": true,
      "required_semantic_fields": ["lifecycle_status"],
      "parameters": {},
      "detection_method": "Blank check on mapped status field.",
      "limitation": "Lifecycle and operational status may share the same source field.",
      "recommended_action": "Confirm status values and normalize to an approved status domain."
    },
    {
      "rule_code": "WW_ATTR_004",
      "name": "Invalid or implausible pipe diameter",
      "description": "Gravity main diameter is zero, negative, nonnumeric, or outside expected wastewater pipe limits.",
      "category": "Attributes",
      "applicable_layer": "wastewater_gravity_main",
      "severity": "medium",
      "enabled": true,
      "required_semantic_fields": ["diameter"],
      "parameters": {"min_inches": 4, "max_inches": 240},
      "detection_method": "Numeric range check on mapped diameter field.",
      "limitation": "Thresholds are QA screening values, not design criteria.",
      "recommended_action": "Verify diameter from source documents and correct invalid values through governed editing."
    },
    {
      "rule_code": "WW_ATTR_005",
      "name": "Missing manhole status",
      "description": "Manhole status is blank.",
      "category": "Attributes",
      "applicable_layer": "wastewater_manhole",
      "severity": "medium",
      "enabled": true,
      "required_semantic_fields": ["lifecycle_status"],
      "parameters": {},
      "detection_method": "Blank check on mapped manhole status field.",
      "limitation": "Lifecycle and operational status may share the same source field.",
      "recommended_action": "Confirm status values and normalize to an approved status domain."
    },
    {
      "rule_code": "WW_ATTR_006",
      "name": "Missing installation date",
      "description": "Mapped installation year/date is blank or unavailable.",
      "category": "Attributes",
      "applicable_layer": "both",
      "severity": "low",
      "enabled": true,
      "required_semantic_fields": ["install_date"],
      "parameters": {},
      "detection_method": "Blank and placeholder check on mapped installation date/year field.",
      "limitation": "Some staged fields contain year-like values rather than true dates.",
      "recommended_action": "Backfill installation date or year from as-builts or project records where authorized."
    },
    {
      "rule_code": "WW_ATTR_007",
      "name": "Invalid domain-coded value",
      "description": "A coded field value is not present in its source domain.",
      "category": "Attributes",
      "applicable_layer": "both",
      "severity": "medium",
      "enabled": true,
      "required_semantic_fields": ["domain_fields"],
      "parameters": {},
      "detection_method": "Compare field values to ArcGIS coded-value domains.",
      "limitation": "Skipped when staged fields have no domains.",
      "recommended_action": "Normalize invalid coded values to the approved domain."
    },
    {
      "rule_code": "WW_ATTR_008",
      "name": "Conflicting lifecycle and operational status",
      "description": "Lifecycle and operational statuses conflict.",
      "category": "Attributes",
      "applicable_layer": "both",
      "severity": "medium",
      "enabled": true,
      "required_semantic_fields": ["lifecycle_status", "operational_status"],
      "parameters": {},
      "detection_method": "Compare mapped lifecycle and operational status values.",
      "limitation": "Skipped when both semantics are represented by the same source field.",
      "recommended_action": "Confirm intended status model and correct conflicting status values."
    },
    {
      "rule_code": "WW_GEOM_001",
      "name": "Null or empty geometry",
      "description": "Feature has no usable geometry.",
      "category": "Geometry",
      "applicable_layer": "both",
      "severity": "high",
      "enabled": true,
      "required_semantic_fields": ["geometry"],
      "parameters": {},
      "detection_method": "ArcPy geometry presence and emptiness check.",
      "limitation": "Does not repair or infer missing geometry.",
      "recommended_action": "Recreate geometry from authoritative source material."
    },
    {
      "rule_code": "WW_GEOM_002",
      "name": "Invalid geometry",
      "description": "Feature geometry appears invalid or unusable.",
      "category": "Geometry",
      "applicable_layer": "both",
      "severity": "high",
      "enabled": true,
      "required_semantic_fields": ["geometry"],
      "parameters": {},
      "detection_method": "Basic geometry validity checks from extracted ArcPy geometry.",
      "limitation": "Full Esri geometry validation may require separate geoprocessing review.",
      "recommended_action": "Review geometry in GIS and repair only through an approved edit workflow."
    },
    {
      "rule_code": "WW_GEOM_003",
      "name": "Very short pipe segment",
      "description": "Gravity main length is below the configured short-segment threshold.",
      "category": "Geometry",
      "applicable_layer": "wastewater_gravity_main",
      "severity": "low",
      "enabled": true,
      "required_semantic_fields": ["geometry"],
      "parameters": {"short_pipe_threshold_feet": 5},
      "detection_method": "Geometry length compared to unit-converted threshold.",
      "limitation": "Short segments can be valid fittings or representation artifacts.",
      "recommended_action": "Review short segment against source geometry and asset model."
    },
    {
      "rule_code": "WW_GEOM_004",
      "name": "Potential duplicate pipe geometry",
      "description": "Gravity main geometry matches another gravity main candidate.",
      "category": "Geometry",
      "applicable_layer": "wastewater_gravity_main",
      "severity": "medium",
      "enabled": true,
      "required_semantic_fields": ["geometry"],
      "parameters": {},
      "detection_method": "Rounded geometry coordinate signature comparison.",
      "limitation": "Reported as candidate duplicates, not confirmed duplicates.",
      "recommended_action": "Review candidate duplicate pipe geometries before editing."
    },
    {
      "rule_code": "WW_GEOM_005",
      "name": "Potential duplicate manhole geometry",
      "description": "Manhole point geometry matches another manhole candidate.",
      "category": "Geometry",
      "applicable_layer": "wastewater_manhole",
      "severity": "medium",
      "enabled": true,
      "required_semantic_fields": ["geometry"],
      "parameters": {},
      "detection_method": "Rounded point coordinate signature comparison.",
      "limitation": "Reported as candidate duplicates, not confirmed duplicates.",
      "recommended_action": "Review candidate duplicate manhole geometries before editing."
    },
    {
      "rule_code": "WW_GEOM_006",
      "name": "Unexpected multipart geometry",
      "description": "Feature geometry is multipart where a single asset part is expected.",
      "category": "Geometry",
      "applicable_layer": "both",
      "severity": "medium",
      "enabled": true,
      "required_semantic_fields": ["geometry"],
      "parameters": {},
      "detection_method": "Multipart flag from ArcPy geometry extraction.",
      "limitation": "Multipart assets may be intentional in legacy source data.",
      "recommended_action": "Review multipart geometry and split only if the asset model requires it."
    },
    {
      "rule_code": "WW_GEOM_007",
      "name": "Pipe self-intersection or geometry anomaly",
      "description": "Gravity main geometry has a screening anomaly such as repeated vertices or closed-line behavior.",
      "category": "Geometry",
      "applicable_layer": "wastewater_gravity_main",
      "severity": "medium",
      "enabled": true,
      "required_semantic_fields": ["geometry"],
      "parameters": {},
      "detection_method": "Coordinate-level anomaly screening.",
      "limitation": "Not a substitute for authoritative geometry validation.",
      "recommended_action": "Review anomalous pipe geometry in GIS."
    },
    {
      "rule_code": "WW_NET_001",
      "name": "Pipe endpoint lacks nearby manhole",
      "description": "Pipe endpoint is not matched to a manhole within endpoint tolerance.",
      "category": "Connectivity",
      "applicable_layer": "wastewater_gravity_main",
      "severity": "high",
      "enabled": true,
      "required_semantic_fields": ["geometry"],
      "parameters": {"endpoint_tolerance_feet": 3},
      "detection_method": "Nearest manhole distance from each pipe endpoint.",
      "limitation": "Proximity does not prove authoritative connectivity.",
      "recommended_action": "Review endpoint and nearby manhole geometry; do not snap automatically."
    },
    {
      "rule_code": "WW_NET_002",
      "name": "Manhole lacks nearby pipe endpoint",
      "description": "Manhole has no pipe endpoint within endpoint tolerance.",
      "category": "Connectivity",
      "applicable_layer": "wastewater_manhole",
      "severity": "medium",
      "enabled": true,
      "required_semantic_fields": ["geometry"],
      "parameters": {"endpoint_tolerance_feet": 3},
      "detection_method": "Endpoint count within tolerance around each manhole.",
      "limitation": "Some manholes may be intentionally isolated or missing associated assets.",
      "recommended_action": "Review isolated manholes against source drawings and asset records."
    },
    {
      "rule_code": "WW_NET_003",
      "name": "Pipe endpoint gap exceeds warning tolerance",
      "description": "Pipe endpoint is farther than warning tolerance from the nearest manhole.",
      "category": "Connectivity",
      "applicable_layer": "wastewater_gravity_main",
      "severity": "medium",
      "enabled": true,
      "required_semantic_fields": ["geometry"],
      "parameters": {"warning_tolerance_feet": 10},
      "detection_method": "Nearest manhole distance from each pipe endpoint.",
      "limitation": "Source geometry may not be snapped.",
      "recommended_action": "Prioritize large endpoint gaps for spatial QA review."
    },
    {
      "rule_code": "WW_NET_004",
      "name": "Pipe crossing without nearby manhole",
      "description": "Pipe geometries cross without a nearby manhole candidate.",
      "category": "Connectivity",
      "applicable_layer": "wastewater_gravity_main",
      "severity": "medium",
      "enabled": true,
      "required_semantic_fields": ["geometry"],
      "parameters": {"endpoint_tolerance_feet": 3},
      "detection_method": "Candidate segment intersection screening with nearby manhole check.",
      "limitation": "Crossings do not automatically mean network connectivity.",
      "recommended_action": "Review crossing candidate and source drawings before adding structures."
    },
    {
      "rule_code": "WW_NET_005",
      "name": "Disconnected wastewater network component",
      "description": "Pipe/manhole proximity graph has multiple connected components.",
      "category": "Connectivity",
      "applicable_layer": "network",
      "severity": "medium",
      "enabled": true,
      "required_semantic_fields": ["geometry"],
      "parameters": {},
      "detection_method": "Union-find graph built from pipe endpoints and nearby manholes.",
      "limitation": "This is proximity-based connectivity, not authoritative topology.",
      "recommended_action": "Review disconnected components against system boundaries and missing source layers."
    },
    {
      "rule_code": "WW_NET_006",
      "name": "Isolated pipe segment",
      "description": "Pipe is in a one-pipe component or has no matched endpoint.",
      "category": "Connectivity",
      "applicable_layer": "wastewater_gravity_main",
      "severity": "medium",
      "enabled": true,
      "required_semantic_fields": ["geometry"],
      "parameters": {},
      "detection_method": "Pipe component and endpoint-match analysis.",
      "limitation": "Force mains, services, and facilities are not yet included.",
      "recommended_action": "Review isolated pipe segment against missing network context."
    },
    {
      "rule_code": "WW_NET_007",
      "name": "Isolated manhole",
      "description": "Manhole has no matched pipe endpoint.",
      "category": "Connectivity",
      "applicable_layer": "wastewater_manhole",
      "severity": "medium",
      "enabled": true,
      "required_semantic_fields": ["geometry"],
      "parameters": {},
      "detection_method": "Manhole endpoint degree from proximity graph.",
      "limitation": "Some manholes may be valid stand-alone structures or require missing assets.",
      "recommended_action": "Review isolated manhole against source drawings and project records."
    },
    {
      "rule_code": "WW_NET_008",
      "name": "Manhole associated with an unusually high number of pipe endpoints",
      "description": "Manhole has endpoint degree above configured threshold.",
      "category": "Connectivity",
      "applicable_layer": "wastewater_manhole",
      "severity": "low",
      "enabled": true,
      "required_semantic_fields": ["geometry"],
      "parameters": {"high_endpoint_degree": 6},
      "detection_method": "Endpoint degree count from proximity graph.",
      "limitation": "Large junction structures may be valid.",
      "recommended_action": "Review high-degree manholes for stacked endpoints or missing structure modeling."
    },
    {
      "rule_code": "WW_FLOW_001",
      "name": "Pipe appears to flow uphill based on mapped upstream and downstream invert fields",
      "description": "Upstream invert is lower than downstream invert.",
      "category": "Connectivity",
      "applicable_layer": "wastewater_gravity_main",
      "severity": "medium",
      "enabled": true,
      "required_semantic_fields": ["upstream_invert", "downstream_invert"],
      "parameters": {},
      "detection_method": "Compare mapped upstream and downstream invert values.",
      "limitation": "Does not infer authoritative flow direction from digitized geometry.",
      "recommended_action": "Verify invert values and pipe direction against authoritative source records."
    },
    {
      "rule_code": "WW_FLOW_002",
      "name": "Missing upstream invert",
      "description": "Mapped upstream invert is blank or zero placeholder.",
      "category": "Connectivity",
      "applicable_layer": "wastewater_gravity_main",
      "severity": "low",
      "enabled": true,
      "required_semantic_fields": ["upstream_invert"],
      "parameters": {},
      "detection_method": "Blank and placeholder check on upstream invert field.",
      "limitation": "Zero values may be placeholders in this source.",
      "recommended_action": "Populate upstream invert from source records where authorized."
    },
    {
      "rule_code": "WW_FLOW_003",
      "name": "Missing downstream invert",
      "description": "Mapped downstream invert is blank or zero placeholder.",
      "category": "Connectivity",
      "applicable_layer": "wastewater_gravity_main",
      "severity": "low",
      "enabled": true,
      "required_semantic_fields": ["downstream_invert"],
      "parameters": {},
      "detection_method": "Blank and placeholder check on downstream invert field.",
      "limitation": "Zero values may be placeholders in this source.",
      "recommended_action": "Populate downstream invert from source records where authorized."
    },
    {
      "rule_code": "WW_FLOW_004",
      "name": "Zero or implausible slope",
      "description": "Calculated pipe slope is zero, negative, or implausibly steep.",
      "category": "Connectivity",
      "applicable_layer": "wastewater_gravity_main",
      "severity": "medium",
      "enabled": true,
      "required_semantic_fields": ["upstream_invert", "downstream_invert", "length"],
      "parameters": {"max_slope_percent": 25},
      "detection_method": "Slope calculated from mapped invert difference and pipe length.",
      "limitation": "Length and elevation units are assumed compatible after source review.",
      "recommended_action": "Verify slope, invert fields, and pipe direction."
    },
    {
      "rule_code": "WW_FLOW_005",
      "name": "Pipe slope conflicts with invert difference and length",
      "description": "Mapped slope conflicts with calculated slope.",
      "category": "Connectivity",
      "applicable_layer": "wastewater_gravity_main",
      "severity": "medium",
      "enabled": true,
      "required_semantic_fields": ["slope", "upstream_invert", "downstream_invert", "length"],
      "parameters": {"slope_tolerance_percent": 0.5},
      "detection_method": "Compare mapped slope to calculated slope.",
      "limitation": "Skipped when no reliable source slope field exists.",
      "recommended_action": "Verify slope calculation and source slope field."
    }
  ]
}
